{
    "packageDirectories": [
        {
            "package": "Nebula Logger Plugin - VdmcSentry",
            "path": "vdmc-sentry-app",
            "dependencies": [
                {
                    "package": "Nebula Logger - Unlocked Package@4.7.0.1"
                }
            ],
            "versionName": "Alpha",
            "versionNumber": "0.1.0.0",
            "versionDescription": "Initial Sentry integration for Nebula Logger",
            "default": false
        },
        {
            "package": "VdmcCore",
            "path": "vdmc-core-app",
            "dependencies": [
                {
                    "package": "Nebula Logger - Unlocked Package@4.7.0.1"
                },
                {
                    "package": "Nebula Logger Plugin - Sentry@0.1.0-0"
                }
            ],
            "versionNumber": "1.0.0",
            "default": true
        }
    ],
    "name": "scratch-nils",
    "namespace": "",
    "sfdcLoginUrl": "https://login.salesforce.com",
    "sourceApiVersion": "53.0",
    "packageAliases": {
        "DependencyInjection": "0Ho09000000sY7PCAU",
        "Nebula Logger - Unlocked Package@4.7.0.1": "04t5Y0000015lXSQAY",
        "Nebula Logger Plugin - Logger Admin Dashboard@0.9.0-0": "04t5Y0000015l3yQAA"
    }
}